{
  "tags": null,
  "ignoreAlpha": false,
  "maxSimultaneousLights": 4,
  "mode": 0,
  "forceAlphaBlending": false,
  "id": "housesMat",
  "name": "housesMat",
  "checkReadyOnEveryCall": false,
  "checkReadyOnlyOnce": false,
  "state": "",
  "alpha": 1,
  "backFaceCulling": true,
  "cullBackFaces": true,
  "sideOrientation": 1,
  "alphaMode": 2,
  "_needDepthPrePass": false,
  "disableDepthWrite": false,
  "disableColorWrite": false,
  "forceDepthWrite": false,
  "depthFunction": 0,
  "separateCullingPass": false,
  "fogEnabled": true,
  "pointSize": 1,
  "zOffset": 0,
  "zOffsetUnits": 0,
  "pointsCloud": false,
  "fillMode": 0,
  "editorData": {
    "locations": [
      {
        "blockId": 12,
        "x": 640,
        "y": -60
      },
      {
        "blockId": 13,
        "x": 400,
        "y": -80
      },
      {
        "blockId": 14,
        "x": 140,
        "y": -140
      },
      {
        "blockId": 15,
        "x": -100,
        "y": -180
      },
      {
        "blockId": 16,
        "x": -100,
        "y": -60
      },
      {
        "blockId": 17,
        "x": 140,
        "y": 0
      },
      {
        "blockId": 18,
        "x": 680,
        "y": 320
      },
      {
        "blockId": 20,
        "x": 420,
        "y": 320
      },
      {
        "blockId": 21,
        "x": 160,
        "y": 320
      },
      {
        "blockId": 22,
        "x": -100,
        "y": 400
      },
      {
        "blockId": 23,
        "x": -380,
        "y": 200
      },
      {
        "blockId": 24,
        "x": -680,
        "y": 200
      },
      {
        "blockId": 25,
        "x": -360,
        "y": 500
      },
      {
        "blockId": 26,
        "x": -620,
        "y": 500
      },
      {
        "blockId": 27,
        "x": -620,
        "y": 600
      }
    ],
    "frames": [],
    "x": 243.70360235956718,
    "y": 125.54078174849994,
    "zoom": 0.7780827681000002
  },
  "customType": "BABYLON.NodeMaterial",
  "outputNodes": [
    12,
    18
  ],
  "blocks": [
    {
      "customType": "BABYLON.VertexOutputBlock",
      "id": 12,
      "name": "VertexOutput",
      "comments": "",
      "visibleInInspector": false,
      "visibleOnFrame": false,
      "target": 1,
      "inputs": [
        {
          "name": "vector",
          "inputName": "vector",
          "targetBlockId": 13,
          "targetConnectionName": "output",
          "isExposedOnFrame": true,
          "exposedPortPosition": -1
        }
      ],
      "outputs": []
    },
    {
      "customType": "BABYLON.TransformBlock",
      "id": 13,
      "name": "WorldPos * ViewProjectionTransform",
      "comments": "",
      "visibleInInspector": false,
      "visibleOnFrame": false,
      "target": 1,
      "inputs": [
        {
          "name": "vector",
          "inputName": "vector",
          "targetBlockId": 14,
          "targetConnectionName": "output",
          "isExposedOnFrame": true,
          "exposedPortPosition": -1
        },
        {
          "name": "transform",
          "inputName": "transform",
          "targetBlockId": 17,
          "targetConnectionName": "output",
          "isExposedOnFrame": true,
          "exposedPortPosition": -1
        }
      ],
      "outputs": [
        {
          "name": "output"
        },
        {
          "name": "xyz"
        }
      ],
      "complementZ": 0,
      "complementW": 1
    },
    {
      "customType": "BABYLON.TransformBlock",
      "id": 14,
      "name": "WorldPos",
      "comments": "",
      "visibleInInspector": false,
      "visibleOnFrame": false,
      "target": 1,
      "inputs": [
        {
          "name": "vector",
          "inputName": "vector",
          "targetBlockId": 15,
          "targetConnectionName": "output",
          "isExposedOnFrame": true,
          "exposedPortPosition": -1
        },
        {
          "name": "transform",
          "inputName": "transform",
          "targetBlockId": 16,
          "targetConnectionName": "output",
          "isExposedOnFrame": true,
          "exposedPortPosition": -1
        }
      ],
      "outputs": [
        {
          "name": "output"
        },
        {
          "name": "xyz"
        }
      ],
      "complementZ": 0,
      "complementW": 1
    },
    {
      "customType": "BABYLON.InputBlock",
      "id": 15,
      "name": "position",
      "comments": "",
      "visibleInInspector": false,
      "visibleOnFrame": false,
      "target": 1,
      "inputs": [],
      "outputs": [
        {
          "name": "output"
        }
      ],
      "type": 8,
      "mode": 1,
      "animationType": 0,
      "min": 0,
      "max": 0,
      "isBoolean": false,
      "matrixMode": 0,
      "isConstant": false,
      "groupInInspector": "",
      "convertToGammaSpace": false,
      "convertToLinearSpace": false
    },
    {
      "customType": "BABYLON.InputBlock",
      "id": 16,
      "name": "World",
      "comments": "",
      "visibleInInspector": false,
      "visibleOnFrame": false,
      "target": 1,
      "inputs": [],
      "outputs": [
        {
          "name": "output"
        }
      ],
      "type": 128,
      "mode": 0,
      "systemValue": 1,
      "animationType": 0,
      "min": 0,
      "max": 0,
      "isBoolean": false,
      "matrixMode": 0,
      "isConstant": false,
      "groupInInspector": "",
      "convertToGammaSpace": false,
      "convertToLinearSpace": false
    },
    {
      "customType": "BABYLON.InputBlock",
      "id": 17,
      "name": "ViewProjection",
      "comments": "",
      "visibleInInspector": false,
      "visibleOnFrame": false,
      "target": 1,
      "inputs": [],
      "outputs": [
        {
          "name": "output"
        }
      ],
      "type": 128,
      "mode": 0,
      "systemValue": 4,
      "animationType": 0,
      "min": 0,
      "max": 0,
      "isBoolean": false,
      "matrixMode": 0,
      "isConstant": false,
      "groupInInspector": "",
      "convertToGammaSpace": false,
      "convertToLinearSpace": false
    },
    {
      "customType": "BABYLON.FragmentOutputBlock",
      "id": 18,
      "name": "FragmentOutput",
      "comments": "",
      "visibleInInspector": false,
      "visibleOnFrame": false,
      "target": 2,
      "inputs": [
        {
          "name": "rgba"
        },
        {
          "name": "rgb",
          "inputName": "rgb",
          "targetBlockId": 20,
          "targetConnectionName": "rgb",
          "isExposedOnFrame": true,
          "exposedPortPosition": -1
        },
        {
          "name": "a",
          "inputName": "a",
          "targetBlockId": 20,
          "targetConnectionName": "a",
          "isExposedOnFrame": true,
          "exposedPortPosition": -1
        }
      ],
      "outputs": [],
      "convertToGammaSpace": false,
      "convertToLinearSpace": false,
      "useLogarithmicDepth": false
    },
    {
      "customType": "BABYLON.TextureBlock",
      "id": 20,
      "name": "scrollingTexture",
      "comments": "",
      "visibleInInspector": false,
      "visibleOnFrame": false,
      "target": 3,
      "inputs": [
        {
          "name": "uv",
          "inputName": "uv",
          "targetBlockId": 21,
          "targetConnectionName": "xy",
          "isExposedOnFrame": true,
          "exposedPortPosition": -1
        },
        {
          "name": "source"
        }
      ],
      "outputs": [
        {
          "name": "rgba"
        },
        {
          "name": "rgb"
        },
        {
          "name": "r"
        },
        {
          "name": "g"
        },
        {
          "name": "b"
        },
        {
          "name": "a"
        },
        {
          "name": "level"
        }
      ],
      "convertToGammaSpace": false,
      "convertToLinearSpace": false,
      "fragmentOnly": false,
      "disableLevelMultiplication": false,
      "texture": {
        "tags": null,
        "url": "/assets/textures/houses.svg",
        "uOffset": 0,
        "vOffset": 0,
        "uScale": 1,
        "vScale": 1,
        "uAng": 0,
        "vAng": 0,
        "wAng": 0,
        "uRotationCenter": 0.5,
        "vRotationCenter": 0.5,
        "wRotationCenter": 0.5,
        "homogeneousRotationInUVTransform": false,
        "isBlocking": true,
        "name": "/assets/textures/houses.svg",
        "hasAlpha": false,
        "getAlphaFromRGB": false,
        "level": 1,
        "coordinatesIndex": 0,
        "optimizeUVAllocation": true,
        "coordinatesMode": 0,
        "wrapU": 1,
        "wrapV": 1,
        "wrapR": 1,
        "anisotropicFilteringLevel": 4,
        "isCube": false,
        "is3D": false,
        "is2DArray": false,
        "gammaSpace": true,
        "invertZ": false,
        "lodLevelInAlpha": false,
        "lodGenerationOffset": 0,
        "lodGenerationScale": 0,
        "linearSpecularLOD": false,
        "isRenderTarget": false,
        "animations": [],
        "invertY": true,
        "samplingMode": 3,
        "_useSRGBBuffer": false
      }
    },
    {
      "customType": "BABYLON.VectorMergerBlock",
      "id": 21,
      "name": "VectorMerger",
      "comments": "",
      "visibleInInspector": false,
      "visibleOnFrame": false,
      "target": 4,
      "inputs": [
        {
          "name": "xyzw "
        },
        {
          "name": "xyz "
        },
        {
          "name": "xy "
        },
        {
          "name": "zw "
        },
        {
          "name": "x",
          "inputName": "x",
          "targetBlockId": 22,
          "targetConnectionName": "output",
          "isExposedOnFrame": true,
          "exposedPortPosition": -1
        },
        {
          "name": "y",
          "inputName": "y",
          "targetBlockId": 23,
          "targetConnectionName": "y",
          "isExposedOnFrame": true,
          "exposedPortPosition": -1
        },
        {
          "name": "z"
        },
        {
          "name": "w"
        }
      ],
      "outputs": [
        {
          "name": "xyzw"
        },
        {
          "name": "xyz"
        },
        {
          "name": "xy"
        },
        {
          "name": "zw"
        }
      ],
      "xSwizzle": "x",
      "ySwizzle": "y",
      "zSwizzle": "z",
      "wSwizzle": "w"
    },
    {
      "customType": "BABYLON.AddBlock",
      "id": 22,
      "name": "Add",
      "comments": "",
      "visibleInInspector": false,
      "visibleOnFrame": false,
      "target": 4,
      "inputs": [
        {
          "name": "left",
          "inputName": "left",
          "targetBlockId": 23,
          "targetConnectionName": "x",
          "isExposedOnFrame": true,
          "exposedPortPosition": -1
        },
        {
          "name": "right",
          "inputName": "right",
          "targetBlockId": 25,
          "targetConnectionName": "output",
          "isExposedOnFrame": true,
          "exposedPortPosition": -1
        }
      ],
      "outputs": [
        {
          "name": "output"
        }
      ]
    },
    {
      "customType": "BABYLON.VectorSplitterBlock",
      "id": 23,
      "name": "VectorSplitter",
      "comments": "",
      "visibleInInspector": false,
      "visibleOnFrame": false,
      "target": 4,
      "inputs": [
        {
          "name": "xyzw"
        },
        {
          "name": "xyz "
        },
        {
          "name": "xy ",
          "inputName": "xy ",
          "targetBlockId": 24,
          "targetConnectionName": "output",
          "isExposedOnFrame": true,
          "exposedPortPosition": -1
        }
      ],
      "outputs": [
        {
          "name": "xyz"
        },
        {
          "name": "xy"
        },
        {
          "name": "zw"
        },
        {
          "name": "x"
        },
        {
          "name": "y"
        },
        {
          "name": "z"
        },
        {
          "name": "w"
        }
      ]
    },
    {
      "customType": "BABYLON.InputBlock",
      "id": 24,
      "name": "uv",
      "comments": "",
      "visibleInInspector": false,
      "visibleOnFrame": false,
      "target": 1,
      "inputs": [],
      "outputs": [
        {
          "name": "output"
        }
      ],
      "type": 4,
      "mode": 1,
      "animationType": 0,
      "min": 0,
      "max": 0,
      "isBoolean": false,
      "matrixMode": 0,
      "isConstant": false,
      "groupInInspector": "",
      "convertToGammaSpace": false,
      "convertToLinearSpace": false
    },
    {
      "customType": "BABYLON.MultiplyBlock",
      "id": 25,
      "name": "Multiply",
      "comments": "",
      "visibleInInspector": false,
      "visibleOnFrame": false,
      "target": 4,
      "inputs": [
        {
          "name": "left",
          "inputName": "left",
          "targetBlockId": 26,
          "targetConnectionName": "output",
          "isExposedOnFrame": true,
          "exposedPortPosition": -1
        },
        {
          "name": "right",
          "inputName": "right",
          "targetBlockId": 27,
          "targetConnectionName": "output",
          "isExposedOnFrame": true,
          "exposedPortPosition": -1
        }
      ],
      "outputs": [
        {
          "name": "output"
        }
      ]
    },
    {
      "customType": "BABYLON.InputBlock",
      "id": 26,
      "name": "Time",
      "comments": "",
      "visibleInInspector": false,
      "visibleOnFrame": false,
      "target": 1,
      "inputs": [],
      "outputs": [
        {
          "name": "output"
        }
      ],
      "type": 1,
      "mode": 0,
      "animationType": 1,
      "min": 0,
      "max": 0,
      "isBoolean": false,
      "matrixMode": 0,
      "isConstant": false,
      "groupInInspector": "",
      "convertToGammaSpace": false,
      "convertToLinearSpace": false,
      "valueType": "number",
      "value": 512.0037599999956
    },
    {
      "customType": "BABYLON.InputBlock",
      "id": 27,
      "name": "speed",
      "comments": "",
      "visibleInInspector": true,
      "visibleOnFrame": false,
      "target": 1,
      "inputs": [],
      "outputs": [
        {
          "name": "output"
        }
      ],
      "type": 1,
      "mode": 0,
      "animationType": 0,
      "min": 0,
      "max": 0,
      "isBoolean": false,
      "matrixMode": 0,
      "isConstant": false,
      "groupInInspector": "",
      "convertToGammaSpace": false,
      "convertToLinearSpace": false,
      "valueType": "number",
      "value": -0.02
    }
  ]
}